[
    {
        "breed_name": "Акита-ину",
        "breed_img": "https://lapkins.ru/upload/iblock/923/923124829b0781ae065bff0951917c74.jpg",
        "breed_descr": "Акита-ину – одна из древнейших пород собак на Земле, выведена в северных регионах Японии. Это гордый, сильный и преданный питомец.",
        "breed_country": "Япония",
        "breed_birth_time": "1964 год",
        "breed_weight": "23 – 39 кг",
        "breed_height": "кобели 64 – 70 см, суки 58 – 64 см",
        "breed_life_expectancy": "10-12 лет"
    },
    {
        "breed_name": "Американская акита",
        "breed_img": "https://lapkins.ru/upload/iblock/e88/e881aa3e59df6650a093dd15e28deb9d.jpg",
        "breed_descr": "Американская акита – сравнительно молодая порода. Это крупная собака с серьезным нравом. Тем, кто найдет к ней подход, станет верным другом.",
        "breed_country": "Япония, США",
        "breed_birth_time": "1955 год",
        "breed_weight": "32-59 кг",
        "breed_height": "кобели 65-70 см, суки 60-65 см",
        "breed_life_expectancy": "10-14 лет"
    },
    {
        "breed_name": "Английский бульдог",
        "breed_img": "https://lapkins.ru/upload/iblock/9a7/9a72d195c7b2eb2cc9a39dba2ab1c233.jpg",
        "breed_descr": "Английский бульдог – мощная, коренастая собака с отлично развитой мускулатурой. За невозмутимый характер, природный ум и чистоплотность бульдога называют «английским джентльменом».",
        "breed_country": "Великобритания",
        "breed_birth_time": "",
        "breed_weight": "кобели 24-25 кг, суки 22-23 кг",
        "breed_height": "около 40 см",
        "breed_life_expectancy": "7-10 лет"
    },
    {
        "breed_name": "Бассет-хаунд",
        "breed_img": "https://lapkins.ru/upload/iblock/178/17857d5d64a088a571464b2a524d0723.jpg",
        "breed_descr": "Бассет-хаунд – массивный брудастый «британец» из секции гончих с экстремально низкой посадкой и длинными ушами.",
        "breed_country": "Великобритания",
        "breed_birth_time": "XX век",
        "breed_weight": "кобели 25-34 кг, суки 20-29 кг",
        "breed_height": "кобели 30-38 см, суки 28-36 см",
        "breed_life_expectancy": "10-12 лет"
    },
    {
        "breed_name": "Белая швейцарская овчарка",
        "breed_img": "https://lapkins.ru/upload/iblock/86d/86d3aeb0ac330511ea104c3bee701e9e.jpg",
        "breed_descr": "Белая швейцарская овчарка – олицетворение красоты и дружелюбия. Нежная, внимательная, понятливая, обладающая прекрасным нравом, она является идеальным компаньоном и верным другом.",
        "breed_country": "Швейцария",
        "breed_birth_time": "",
        "breed_weight": "кобели 30 – 40 кг, суки 25 – 35 кг",
        "breed_height": "кобели 58 – 66 см, суки 53 – 61 см",
        "breed_life_expectancy": "13 – 15 лет"
    },
    {
        "breed_name": "Бернский зенненхунд",
        "breed_img": "https://lapkins.ru/upload/iblock/d6f/d6fa2b8515196659e82bd805a98aaa97.jpg",
        "breed_descr": "Бернский зенненхунд (бернская овчарка) – ласковый и обаятельный гигант с самой добродушной «улыбкой» на свете. Представители этой породы – идеальные компаньоны, обладающие врожденным чувством такта и необычайно миролюбивым характером.",
        "breed_country": "Швейцария",
        "breed_birth_time": "1910 год",
        "breed_weight": "кобели 39-50 кг, суки 36-48 кг",
        "breed_height": "кобели 64-70 см, суки",
        "breed_life_expectancy": "8 – 10 лет"
    },
    {
        "breed_name": "Бишон фризе",
        "breed_img": "https://lapkins.ru/upload/iblock/6f3/6f3dac95ba1fea52efed069f2e512b1f.jpg",
        "breed_descr": "Бишон фризе (французская болонка) – миниатюрный плюшевый «антидепрессант» и обаятельный шалун, с которым не придется скучать.",
        "breed_country": "Франция, Бельгия",
        "breed_birth_time": "",
        "breed_weight": "2,5-3 кг",
        "breed_height": "25-30 см",
        "breed_life_expectancy": "12-15 лет"
    },
    {
        "breed_name": "Бладхаунд",
        "breed_img": "https://lapkins.ru/upload/iblock/c60/c6035673cdcf3119e45483914d43b623.jpg",
        "breed_descr": "Бладхаунд – один из самых крупных и древних представителей гончей группы. Это собака-следопыт, обладатель феноменального нюха, а также неординарного имиджа, включающего в себя длинные, свернутые в трубку уши и «стекающий» профиль морды.",
        "breed_country": "Бельгия",
        "breed_birth_time": "XIII век",
        "breed_weight": "кобели 46 – 54 кг, суки 40 – 48 кг",
        "breed_height": "кобели 64 – 72 см, суки 58 – 66 см",
        "breed_life_expectancy": "10 – 12 лет"
    },
    {
        "breed_name": "Большой швейцарский зенненхунд",
        "breed_img": "https://lapkins.ru/upload/iblock/554/k4gofuguxmwv8aluv90vbq9pk7a4bkht.jpeg",
        "breed_descr": "Большой швейцарский зенненхунд – крупная горная собака трехцветного окраса, выведенная в Альпах. Относится к рабочим породам, использовавшимся для загона скота, охраны жилища и перевозки небольших грузов в сложных условиях гористой местности.",
        "breed_country": "Швейцария",
        "breed_birth_time": "1954 год",
        "breed_weight": "кобели 50-64 кг, суки 48-54 кг",
        "breed_height": "кобели 65-72 см, суки 60-69 см",
        "breed_life_expectancy": "9-12 лет"
    },
    {
        "breed_name": "Дирхаунд",
        "breed_img": "https://lapkins.ru/upload/iblock/2ac/lcjdjhtgh2slq2pohp4p1mfqgn80lxa7.jpg",
        "breed_descr": "Дирхаунд (шотландская оленья борзая) – жесткошерстная охотничья собака, превосходно работающая в условиях гористой и пересеченной местности. Внешне напоминает ирландского волкодава, но с более изящным силуэтом. Выводилась для охоты на копытных.",
        "breed_country": "Шотландия",
        "breed_birth_time": "1955 год",
        "breed_weight": "кобели ≈ 45,5 кг, суки ≈ 36 кг",
        "breed_height": "кобели от 76 см, суки от 71 см",
        "breed_life_expectancy": "8-11 лет"
    },
    {
        "breed_name": "Золотистый ретривер",
        "breed_img": "https://lapkins.ru/upload/iblock/249/249483cc29c8f7316027872ed67ca526.jpg",
        "breed_descr": "Золотистый ретривер – отличный компаньон и лучший друг охотника. Добродушен, спокоен, великолепно апортирует подстреленную дичь.",
        "breed_country": "Великобритания",
        "breed_birth_time": "XIX век",
        "breed_weight": "кобели 26-41 кг, суки 25-37 кг",
        "breed_height": "кобели 56-61 см, суки 51-56 см",
        "breed_life_expectancy": "12 – 13 лет"
    },
    {
        "breed_name": "Испанский мастиф",
        "breed_img": "https://lapkins.ru/upload/iblock/7b7/7b7851162ac25c8877fb43584c1aaab7.jpg",
        "breed_descr": "Испанский мастиф скрывает добродушный характер под внешностью угрюмого гиганта и демонстрирует его лишь близким людям. Из собаки получится не только отменный сторож, но и друг на долгие годы. Главное – найти к животному подход и наслаждаться его обществом!",
        "breed_country": "Испания",
        "breed_birth_time": "",
        "breed_weight": "70-120 кг",
        "breed_height": "кобели не менее 77 см, суки не менее 72 см",
        "breed_life_expectancy": "9-11 лет"
    },
    {
        "breed_name": "Кавалер-кинг-чарльз-спаниель",
        "breed_img": "https://lapkins.ru/upload/iblock/b48/b485acd675a27aac77d3a42829a213ed.jpg",
        "breed_descr": "Кавалер-кинг-чарльз-спаниель – развеселый лохматый непоседа, обладающий выразительной, кокетливой внешностью и добродушным характером. Оживит собственным присутствием любой дом и отлично справится с ролью надежного компаньона.",
        "breed_country": "Великобритания",
        "breed_birth_time": "XVII век",
        "breed_weight": "от 5,5 до 8 кг",
        "breed_height": "до 32 см",
        "breed_life_expectancy": "11-12 лет"
    },
    {
        "breed_name": "Лабрадор-ретривер",
        "breed_img": "https://lapkins.ru/upload/iblock/f09/f09005e451fc6fcacdbcabc6d2f1de09.jpg",
        "breed_descr": "Лабрадор – одна из самых популярных пород в современном мире. Это идеальный питомец для семей с детьми, охотников, спасателей и людей с ограниченными возможностями.",
        "breed_country": "Великобритания",
        "breed_birth_time": "XIX век",
        "breed_weight": "кобели 27-34 кг, суки 25-32 кг",
        "breed_height": "кобели 56-57 см, суки 54-56 см",
        "breed_life_expectancy": "12-13 лет"
    },
    {
        "breed_name": "Леонбергер",
        "breed_img": "https://lapkins.ru/upload/iblock/3f8/3f8ffbf9639e2c6370001b553ee32280.jpg",
        "breed_descr": "Леонбергер – порода крупногабаритных лохматых собак с черной маской на морде, выведенная в одном из юго-западных регионов Германии.",
        "breed_country": "Германия",
        "breed_birth_time": "",
        "breed_weight": "кобели 59-77 кг, суки 45-59 кг",
        "breed_height": "кобели 74-80 см, суки 61-74 см",
        "breed_life_expectancy": "9-11 лет"
    },
    {
        "breed_name": "Маремма-абруццкая овчарка",
        "breed_img": "https://lapkins.ru/upload/iblock/24a/24a1848f520299b6b7fb457fbe53ef7c.jpg",
        "breed_descr": "Маремма-абруццкая овчарка (маремма) – итальянская порода крупных белых собак, выведенных специально для охраны и перегона овец. Всех особей отличает врожденное недоверие к незнакомым людям, а также умение самостоятельно анализировать ситуацию и принимать решения. ",
        "breed_country": "Италия",
        "breed_birth_time": "",
        "breed_weight": "кобели 35-35 кг, суки 30-40 кг",
        "breed_height": "кобели 65-73 см, суки 60-68 см",
        "breed_life_expectancy": "11-14 лет"
    },
    {
        "breed_name": "Миттельшнауцер",
        "breed_img": "https://lapkins.ru/upload/iblock/075/07530c91362e094d1e47898176bbda4e.jpg",
        "breed_descr": "Миттельшнауцер – собака из группы шнауцеров, зарекомендовавшая себя отличным сторожем и поисковиком. Отличительные черты породы – квадратный формат туловища, эффектные «брови» и «бородка» из длинного украшающего волоса.",
        "breed_country": "Германская империя",
        "breed_birth_time": "1879",
        "breed_weight": "17-25 кг",
        "breed_height": "45-50 см",
        "breed_life_expectancy": "13-15 лет"
    },
    {
        "breed_name": "Мопс",
        "breed_img": "https://lapkins.ru/upload/iblock/130/1309222f033fb6928ea065578276ab44.jpg",
        "breed_descr": "Мопс является древней и неизменно популярной на протяжении всей своей истории породой. Это прекрасная собака-компаньон для городских жителей.",
        "breed_country": "Древний Китай",
        "breed_birth_time": "",
        "breed_weight": "6-8 кг",
        "breed_height": "28-32 см",
        "breed_life_expectancy": "13-14 лет"
    },
    {
        "breed_name": "Немецкая овчарка",
        "breed_img": "https://lapkins.ru/upload/iblock/212/212adec96be4631fe2fa0584225b83ff.jpg",
        "breed_descr": "Немецкая овчарка живет бок о бок с человеком с незапамятных времен. Сегодня она является одной из самых популярных и узнаваемых пород собак на планете.",
        "breed_country": "Германия",
        "breed_birth_time": "конец XIX века",
        "breed_weight": "кобели 30-40 кг, суки 22-32 кг",
        "breed_height": "кобели 60-65 см, суки 55-60 см",
        "breed_life_expectancy": "10-13 лет"
    },
    {
        "breed_name": "Ньюфаундленд",
        "breed_img": "https://lapkins.ru/upload/iblock/4a8/4a86cff4ab81d72fe1dea71242323a8c.jpg",
        "breed_descr": "Ньюфаундленд – огромная мощная собака с эффектной внешностью и великолепным характером. Цель ее существования – служение людям.",
        "breed_country": "Канада",
        "breed_birth_time": "",
        "breed_weight": "кобели ~68 кг, суки ~54 кг",
        "breed_height": "кобели ~71 см, суки ~66 см",
        "breed_life_expectancy": "9-11 лет"
    },
    {
        "breed_name": "Перуанская голая собака",
        "breed_img": "https://lapkins.ru/upload/iblock/558/kvicyyh9ffs2zagi5skzqr36w6dootpp.jpg",
        "breed_descr": "Перуанская голая собака – порода бесшерстных, реже – покрытых шерстью собак с территории современного Перу. Относится к породам примитивного типа, максимально приближенным к волкоподобным предкам.",
        "breed_country": "Перу",
        "breed_birth_time": "300 г. до н. э. — 1460 г. н. э.",
        "breed_weight": "малые: 4-8 кг; средние: 8-12 кг; большие: 12-30 кг",
        "breed_height": "малые: 25-40 см; средние: 41-50 см; большие: 51-65 см",
        "breed_life_expectancy": "12-15 лет"
    },
    {
        "breed_name": "Сенбернар",
        "breed_img": "https://lapkins.ru/upload/iblock/775/775490d24dae51e61bb57ba43630676f.jpg",
        "breed_descr": "Сенбернар – обаятельный гигант с миролюбивым характером и немного печальным взглядом. Считается типичной семейной собакой, но при правильно подобранном курсе дрессировки сможет стать отличным спасателем или сторожем. Спокоен, дисциплинирован, искренне любит детей.",
        "breed_country": "Швейцария",
        "breed_birth_time": "середина XVII века",
        "breed_weight": "не менее 70 кг",
        "breed_height": "кобели 70-90 см, суки 65-80 см",
        "breed_life_expectancy": "9-11 лет"
    },
    {
        "breed_name": "Тибетский мастиф",
        "breed_img": "https://lapkins.ru/upload/iblock/fc7/fc7dc33d839fd89dd524200e54eb6b14.jpg",
        "breed_descr": "Тибетский мастиф – огромный красавец, который примечателен мощными габаритами. Впрочем, его внешнее сходство с царём зверей нисколько не умаляет добродушия.",
        "breed_country": "Тибет",
        "breed_birth_time": "",
        "breed_weight": "64-78 кг",
        "breed_height": "кобели от 66 см, суки от 61 см",
        "breed_life_expectancy": "10-11 лет"
    },
    {
        "breed_name": "Чесапик-бей-ретривер",
        "breed_img": "https://lapkins.ru/upload/iblock/760/q081nva4oresbwcnramkklvou32filaz.jpg",
        "breed_descr": "Чесапик-бей-ретривер – американская порода собак, выведенная специально для охоты на водоплавающую дичь в жестких погодных условиях.",
        "breed_country": "США",
        "breed_birth_time": "1878 год",
        "breed_weight": "кобели 29,5-36,5 кг, суки 25-32кг",
        "breed_height": "кобели 58-66 см, суки 53-61 см",
        "breed_life_expectancy": "10-13 лет"
    },
    {
        "breed_name": "Чехословацкий влчак",
        "breed_img": "https://lapkins.ru/upload/iblock/1b4/5eg2rkx12crs8j7x7qvg08tf4p84l3pg.jpg",
        "breed_descr": "Чехословацкий влчак (чехословацкая волчья собака) – крупная собака c универсальными рабочими качествами, выведенная путем скрещивания немецкой овчарки с карпатским волком. На сегодняшний день не относится к гибридным породам. Входит в группу пастушьих и скотогонных собак.",
        "breed_country": "Чехословакия",
        "breed_birth_time": "",
        "breed_weight": "кобели от 26 кг, суки от 20 кг",
        "breed_height": "кобели от 65 см, суки от 60 см",
        "breed_life_expectancy": "12-15 лет"
    },
    {
        "breed_name": "Шарпей",
        "breed_img": "https://lapkins.ru/upload/iblock/6eb/6eb68a1aa8f617f075d30573d4c50c8d.jpg",
        "breed_descr": "Шарпей когда-то был универсальной рабочей собакой, которая выполняла функции сторожа, пастуха и защитника стад, охотника, даже профессионального бойца. Сегодня их чаще всего заводят не для охраны, а в качестве компаньона.",
        "breed_country": "Китай",
        "breed_birth_time": "202 г. до н. э.",
        "breed_weight": "18-35 кг",
        "breed_height": "40-51 см",
        "breed_life_expectancy": "10-12 лет"
    },
    {
        "breed_name": "Ши-тцу",
        "breed_img": "https://lapkins.ru/upload/iblock/b0b/b0b0364aa02f21000841862330af0792.jpg",
        "breed_descr": "Ши-тцу – собака-компаньон с длинной атласной шерстью, придающей животному сходство с цветком хризантемы. Имеет азиатские корни, отличается уравновешенным характером и сильным чувством привязанности к хозяину.",
        "breed_country": "Тибет",
        "breed_birth_time": "XVI век",
        "breed_weight": "4-7 кг",
        "breed_height": "до 27 см",
        "breed_life_expectancy": "12-14 лет"
    },
    {
        "breed_name": "Шотландская овчарка (колли)",
        "breed_img": "https://lapkins.ru/upload/iblock/128/1286da8e4827f9df9e47173635fbfca5.jpg",
        "breed_descr": "Шотландская овчарка (колли) – крупная пастушья собака с удлиненной вытянутой мордой и обаятельным лукавым взглядом. С конца 90-х разводится в двух независимых друг от друга разновидностях – длинношерстной и короткошерстной.",
        "breed_country": "Великобритания",
        "breed_birth_time": "XVII век",
        "breed_weight": "кобели 26-34 кг, суки 19-26 кг",
        "breed_height": "кобели 56-61 см, суки 51-56 см",
        "breed_life_expectancy": "12-13 лет"
    },
    {
        "breed_name": "Японский шпиц",
        "breed_img": "https://lapkins.ru/upload/iblock/a9f/a9f6004878eea81bc3aac1ca4426c15e.jpg",
        "breed_descr": "Японский шпиц – небольшая собака из группы шпицев с пушистой шерсткой белоснежного окраса. Представители породы отличаются живым темпераментом, но вполне управляемы и легко дрессируются. ",
        "breed_country": "Япония",
        "breed_birth_time": "1920-1930-е гг.",
        "breed_weight": "5-8 кг",
        "breed_height": "28-36 см",
        "breed_life_expectancy": "10-16 лет"
    }
]